wipe_clean/__init__.py
wipe_clean/_rich/__init__.py
wipe_clean/_rich/_windows.py
wipe_clean/_rich/control.py
wipe_clean/_rich/simple_console.py
wipe_clean/brush.py
wipe_clean/fun.py
wipe_clean/main.py
wipe_clean/path.py
wipe_clean/renderer.py
wipe_clean/screen.py
wipe_clean/utils.py
wipe_clean-0.3.1.dist-info/entry_points.txt
wipe_clean-0.3.1.dist-info/LICENSE
wipe_clean-0.3.1.dist-info/WHEEL
wipe_clean-0.3.1.dist-info/METADATA
wipe_clean-0.3.1.dist-info/RECORD
