Metadata-Version: 2.1
Name: wipe-clean
Version: 0.3.1
Summary: Clear your terminal in a ritual way. Zero dependency.
Home-page: https://github.com/wenoptics/python-wipe-clean
Author: wenoptk
Author-email: wenoptics@gmail.com
Requires-Python: >=3.6.2,<4.0.0
Classifier: Development Status :: 4 - Beta
Classifier: Environment :: Console
Classifier: License :: OSI Approved :: MIT License
Classifier: Operating System :: OS Independent
Classifier: Programming Language :: Python :: 3
Classifier: Programming Language :: Python :: 3.10
Classifier: Programming Language :: Python :: 3.7
Classifier: Programming Language :: Python :: 3.8
Classifier: Programming Language :: Python :: 3.9
Classifier: Typing :: Typed
Project-URL: Bug Tracker, https://github.com/wenoptics/python-wipe-clean/issues
Project-URL: Repository, https://github.com/wenoptics/python-wipe-clean
